paragraph2actions/__init__.py
paragraph2actions/actions.py
paragraph2actions/analysis.py
paragraph2actions/conversion_utils.py
paragraph2actions/converter_interface.py
paragraph2actions/data_augmentation.py
paragraph2actions/data_splitting.py
paragraph2actions/default_converters.py
paragraph2actions/introspection.py
paragraph2actions/misc.py
paragraph2actions/paragraph_translator.py
paragraph2actions/py.typed
paragraph2actions/readable_converter.py
paragraph2actions/repr_converter.py
paragraph2actions/sentence_postprocessor.py
paragraph2actions/sentencepiece_tokenizer.py
paragraph2actions/translator.py
paragraph2actions/utils.py
paragraph2actions/augmentation/__init__.py
paragraph2actions/augmentation/action_attribute_augmenter.py
paragraph2actions/augmentation/augmenter.py
paragraph2actions/augmentation/compound_name_augmenter.py
paragraph2actions/augmentation/compound_quantity_augmenter.py
paragraph2actions/augmentation/duration_augmenter.py
paragraph2actions/augmentation/substitution_augmenter.py
paragraph2actions/augmentation/temperature_augmenter.py
paragraph2actions/postprocessing/__init__.py
paragraph2actions/postprocessing/action_postprocessor.py
paragraph2actions/postprocessing/drysolution_postprocessor.py
paragraph2actions/postprocessing/duplicate_actions_postprocessor.py
paragraph2actions/postprocessing/filter_postprocessor.py
paragraph2actions/postprocessing/initial_makesolution_postprocessor.py
paragraph2actions/postprocessing/noaction_postprocessor.py
paragraph2actions/postprocessing/postprocessor_combiner.py
paragraph2actions/postprocessing/purify_postprocessor.py
paragraph2actions/postprocessing/same_temperature_postprocessor.py
paragraph2actions/postprocessing/wait_postprocessor.py
paragraph2actions/scripts/__init__.py
paragraph2actions/scripts/calculate_metrics.py
paragraph2actions/scripts/create_sentencepiece_tokenizer.py
paragraph2actions/scripts/generate_samples_to_annotate.py
paragraph2actions/scripts/tokenize_with_sentencepiece.py
paragraph2actions-1.5.0.dist-info/LICENSE
paragraph2actions-1.5.0.dist-info/METADATA
paragraph2actions-1.5.0.dist-info/WHEEL
paragraph2actions-1.5.0.dist-info/entry_points.txt
paragraph2actions-1.5.0.dist-info/top_level.txt
paragraph2actions-1.5.0.dist-info/RECORD
