Metadata-Version: 2.1
Name: paragraph2actions
Version: 1.5.0
Summary: Extraction of actions from experimental procedures
Home-page: https://github.com/rxn4chemistry/paragraph2actions
Author: IBM RXN team
Author-email: rxn4chemistry@zurich.ibm.com
License: MIT
Project-URL: Repository, https://github.com/rxn4chemistry/paragraph2actions
Classifier: Operating System :: OS Independent
Classifier: Programming Language :: Python :: 3
Classifier: Programming Language :: Python :: 3.6
Classifier: Programming Language :: Python :: 3.7
Classifier: Programming Language :: Python :: 3.8
Requires-Python: >=3.6
License-File: LICENSE
Requires-Dist: attrs >=19.1.0
Requires-Dist: click >=7.0
Requires-Dist: nltk >=3.4.5
Requires-Dist: rxn-onmt-utils >=1.1.0
Requires-Dist: sentencepiece >=0.1.83
Requires-Dist: textdistance >=4.1.5
Provides-Extra: cde
Requires-Dist: ChemDataExtractor >=1.3.0 ; extra == 'cde'
Provides-Extra: dev
Requires-Dist: bump2version >=1.0.1 ; extra == 'dev'
Requires-Dist: black >=23.1.0 ; extra == 'dev'
Requires-Dist: isort >=5.12.0 ; extra == 'dev'
Requires-Dist: flake8 >=6.0.0 ; extra == 'dev'
Requires-Dist: mypy >=1.0.0 ; extra == 'dev'
Requires-Dist: types-setuptools >=57.4.14 ; extra == 'dev'
